{
  "version": 3,
  "requesterUsername": "devopstanvir",
  "requesterAvatarIconUri": {
    "$mid": 1,
    "path": "/u/237455656",
    "scheme": "https",
    "authority": "avatars.githubusercontent.com",
    "query": "v=4"
  },
  "responderUsername": "GitHub Copilot",
  "responderAvatarIconUri": {
    "id": "copilot"
  },
  "initialLocation": "panel",
  "requests": [],
  "sessionId": "9ea8d4bd-4798-4251-86ca-71c654fa9f6b",
  "creationDate": 1761564168007,
  "isImported": false,
  "lastMessageDate": 1761564168007
}